unicov.py
unicov-0.0.1.dist-info/LICENSE
unicov-0.0.1.dist-info/METADATA
unicov-0.0.1.dist-info/WHEEL
unicov-0.0.1.dist-info/top_level.txt
unicov-0.0.1.dist-info/RECORD
